py_partiql_parser/__init__.py
py_partiql_parser/exceptions.py
py_partiql_parser/_internal/__init__.py
py_partiql_parser/_internal/clause_tokenizer.py
py_partiql_parser/_internal/csv_converter.py
py_partiql_parser/_internal/delete_parser.py
py_partiql_parser/_internal/from_parser.py
py_partiql_parser/_internal/insert_parser.py
py_partiql_parser/_internal/json_parser.py
py_partiql_parser/_internal/parser.py
py_partiql_parser/_internal/select_parser.py
py_partiql_parser/_internal/update_parser.py
py_partiql_parser/_internal/utils.py
py_partiql_parser/_internal/where_parser.py
py_partiql_parser/_packages/__init__.py
py_partiql_parser/_packages/boto3/__init__.py
py_partiql_parser/_packages/boto3/types.py
py_partiql_parser-0.6.2.dist-info/METADATA
py_partiql_parser-0.6.2.dist-info/WHEEL
py_partiql_parser-0.6.2.dist-info/licenses/LICENSE
py_partiql_parser-0.6.2.dist-info/RECORD
